rynput/__init__.py
rynput/property.py
rynput/property_group.py
rynput/validator.py
rynput/validators/__init__.py
rynput/validators/bool.py
rynput/validators/float.py
rynput/validators/integer.py
rynput/validators/option.py
rynput/validators/regex.py
rynput/validators/semver.py
rynput/validators/string.py
rynput/validators/switch.py
rynput-1.0.3.dist-info/licenses/LICENSE.md
rynput-1.0.3.dist-info/METADATA
rynput-1.0.3.dist-info/WHEEL
rynput-1.0.3.dist-info/top_level.txt
rynput-1.0.3.dist-info/RECORD
