Metadata-Version: 2.4
Name: rynput
Version: 1.0.3
Summary: Python tools for typed input validation.
Author-email: Jacob Thomas <jacob.thomas7852@gmail.com>
License-Expression: MIT
Project-URL: Homepage, https://github.com/jacob-thomas7/rynput
Classifier: Programming Language :: Python :: 3
Classifier: Operating System :: OS Independent
Requires-Python: >=3.9
License-File: LICENSE.md
Dynamic: license-file
